qq/__init__.py
qq/application.py
qq/context.py
qq/errors.py
qq/finder.py
qq/initializers.py
qq/injectors.py
qq/plugin.py
qq/plugin_container.py
qq/plugins/__init__.py
qq/plugins/celery/__init__.py
qq/plugins/celery/finder.py
qq/plugins/celery/plugin.py
qq/plugins/logging.py
qq/plugins/redis.py
qq/plugins/settings.py
qq/plugins/sqlalchemy/__init__.py
qq/plugins/sqlalchemy/alembic.py
qq/plugins/sqlalchemy/consts.py
qq/plugins/sqlalchemy/exceptions.py
qq/plugins/sqlalchemy/injectors.py
qq/plugins/sqlalchemy/plugin.py
qq/plugins/sqlalchemy/tests/__init__.py
qq/plugins/sqlalchemy/tests/test_exceptions.py
qq/plugins/sqlalchemy/tests/test_plugin.py
qq/plugins/tests/__init__.py
qq/plugins/tests/test_logging.py
qq/plugins/tests/test_redis.py
qq/plugins/tests/test_settings.py
qq/plugins/types.py
qq/testing.py
qq/tests/__init__.py
qq/tests/test_configurator.py
qq/tests/test_context_manager.py
qq/tests/test_finder.py
qq/tests/test_inicjators.py
qq/tests/test_injector_yield.py
qq/tests/test_plugin.py
qq/tests/test_plugin_container.py
qq/types.py
quackquack-1.3.3.dist-info/METADATA
quackquack-1.3.3.dist-info/WHEEL
quackquack-1.3.3.dist-info/RECORD
