Metadata-Version: 2.3
Name: quackquack
Version: 1.3.3
Summary: Quack Quack: A simple application initializator
License: MIT
Author: Dominik Dlugajczyk
Author-email: msocek@gmail.com
Requires-Python: >=3.8
Classifier: License :: OSI Approved :: MIT License
Classifier: Programming Language :: Python :: 3
Classifier: Programming Language :: Python :: 3.8
Classifier: Programming Language :: Python :: 3.9
Classifier: Programming Language :: Python :: 3.10
Classifier: Programming Language :: Python :: 3.11
Classifier: Programming Language :: Python :: 3.12
Classifier: Programming Language :: Python :: 3.13
Provides-Extra: alembic
Provides-Extra: celery
Provides-Extra: developer
Provides-Extra: redis
Provides-Extra: sqlalchemy
Requires-Dist: alembic (>=1.0.9,<2.0.0) ; extra == "alembic" or extra == "developer"
Requires-Dist: celery (>=5.2.2) ; extra == "celery" or extra == "developer"
Requires-Dist: python-dateutil (>=2.8.2,<3.0.0)
Requires-Dist: redis (>=3.2.1,<5.0.0) ; extra == "redis" or extra == "developer"
Requires-Dist: sqlalchemy (>=2.0.39,<3.0.0) ; extra == "sqlalchemy" or extra == "developer"
Project-URL: Homepage, https://github.com/socek/quackquack
